{
	"module": "DateDayTimeYear",
	"icon": "time",
	"description": "Nutzer fragt nach der Zeit, dem Datum, dem Wochentag oder dem Jahr",
	"slotTypes": [],
	"intents": [
		{
			"name": "GetDay",
			"description": "Nutzer fragt nach dem heutigen Wochentag",
			"enabledByDefault": true,
			"utterances": [
				"Weißt du welcher Tag heute ist",
				"Kannst du mir sagen, welcher Tag heute ist, bitte",
				"Kannst du mir sagen, welcher Tag heute ist",
				"Bitte kannst du mir sagen, welcher Tag heute ist",
				"Kannst du mir bitte sagen, welcher Tag heute ist",
				"Bitte könntest du mir sagen, welcher Tag heute ist",
				"könntest du mir bitte sagen, welcher Tag heute ist",
				"könntest du mir sagen, welcher Tag heute ist, bitte",
				"könntest du mir sagen, welcher Tag heute ist",
				"Bitte kannst du mir den Tag sagen",
				"kannst du mir bitte den Tag sagen",
				"kannst du mir den Tag sagen, bitte",
				"kannst du mir den Tag sagen",
				"Was ist der Tag bitte",
				"Was ist der Tag",
				"Was ist der heutige Tag",
				"Was ist der heutige Tag, bitte",
				"Welchen Wochentag haben wir",
				"Welchen Wochentag haben wir, bitte",
				"Welcher Tag ist",
				"Welcher Tag ist, bitte",
				"Welchen Tag haben wir",
				"Welchen Tag haben wir, bitte"
			],
			"slots": []
		},
		{
			"name": "GetDate",
			"description": "Nutzer fragt nach dem Datum",
			"enabledByDefault": true,
			"utterances": [
				"Weißt du, was das heutige Datum ist?",
				"Weißt du, was das Datum ist?",
				"Bitte, was ist das Datum?",
				"Könntest du mir bitte das Datum mitteilen?",
				"Könntest du mir bitte den Termin nennen?",
				"Könntest du mir bitte den Termin sagen?",
				"Nenne mir bitte das Datum.",
				"Nenn mir bitte das Datum.",
				"Bitte nenne mir das Datum",
				"Bitte nenn mir das Datum",
				"Bitte sag mir das Datum",
				"Kannst du mir das Datum sagen.",
				"Könntest du mir das Datum sagen.",
				"was ist das Datum bitte?",
				"wie lautet das Datum bitte?",
				"Welches Datum haben wir?",
				"Bitte gib mir das Datum",
				"was ist das Datum",
				"wie lautet das Datum",
				"was ist das heutige Datum?",
				"Wie lautet das heutige Datum?",
				"Gib mir das Datum",
				"Wie ist das Datum",
				"Wie ist das Datum bitte?"
			],
			"slots": []
		},
		{
			"name": "GetTime",
			"description": "Nutzer fragt nach der Uhrzeit",
			"enabledByDefault": true,
			"utterances": [
				"Bitte gib mir die Uhrzeit.",
				"Bitte kann ich dich nach der Uhrzeit fragen.",
				"Kann ich dich nach der Uhrzeit fragen, bitte?",
				"Kann ich dich nach der Uhrzeit fragen.",
				"Könntest du mir bitte die Uhreit sagen.",
				"Könntest du mir bitte die Uhrzeit mitteilen.",
				"Bitte könntest du mir die Uhrzeit mitteilen.",
				"Könntest du mir die Uhrzeit sagen.",
				"Wie viel Uhr haben wir jetzt?",
				"Wie viel Uhr haben wir gerade",
				"Wie spät ist es",
				"Wie spät ist es jetzt",
				"Wie spät ist es gerade",
				"Wie spät ist es aktuell",
				"Uhrzeit bitte",
				"Wie spät ist es bitte?",
				"Bitte teile mir die Uhrzeit mit.",
				"Bitte teil mir die Uhrzeit mit.",
				"Bitte nenne mir die Uhrzeit.",
				"Bitte nenn mir die Uhrzeit.",
				"Gib mir die Uhrzeit, bitte.",
				"Sag mir, wie spät es ist.",
				"Sag mir die Uhrzeit",
				"Kannst du mir sagen, wie spät es ist.",
				"Wie viel Uhr ist es?"
			],
			"slots": []
		},
		{
			"name": "GetYear",
			"description": "Nutzer fragt nach dem Jahr",
			"enabledByDefault": true,
			"utterances": [
				"Kannst du mir das Jahr sagen",
				"Was ist das aktuelle Jahr",
				"Könntest du mir sagen welches Jahr wir haben",
				"Könntest du mir sagen welches Jahr wir aktuell haben",
				"Was ist das Jahr",
				"Was ist das Jahr, bitte",
				"In welchem Jahr sind wir",
				"In welchem Jahr sind wir aktuell",
				"Gib mir das Jahr",
				"Welches Jahr haben wir"
			],
			"slots": []
		}
	]
}